gonzo_card_games/__init__.py
gonzo_card_games/CardDeck/Card.py
gonzo_card_games/CardDeck/CardDeck.py
gonzo_card_games/CardDeck/__init__.py
gonzo_card_games/RatScrew/Game.py
gonzo_card_games/RatScrew/Player.py
gonzo_card_games/RatScrew/RoundCardStack.py
gonzo_card_games/RatScrew/__init__.py
gonzo_card_games/Templates/CardGameTemplate.py
gonzo_card_games/Templates/__init__.py
gonzo_card_games-0.0.2.dist-info/METADATA
gonzo_card_games-0.0.2.dist-info/WHEEL
gonzo_card_games-0.0.2.dist-info/licenses/LICENSE
gonzo_card_games-0.0.2.dist-info/RECORD
