Metadata-Version: 2.4
Name: gonzo_card_games
Version: 0.0.2
Summary: Virtualization of card games with a standard deck
Project-URL: Homepage, https://github.com/gonz1247/gonzo_card_games
Project-URL: Repository, https://github.com/gonz1247/gonzo_card_games.git
Project-URL: Documentation, https://gonz1247.github.io/gonzo_card_games/
Author-email: "Alejandro (Gonzo) Gonzalez" <agonzalez1043@gmail.com>
License-Expression: MIT
License-File: LICENSE
Keywords: Gonzo,card,card deck,cards,egyption rat screw,egyption wrath,rat screw
Classifier: Development Status :: 3 - Alpha
Classifier: Programming Language :: Python
Requires-Python: >=3.10
